ama_xiv_combat_sim/__init__.py
ama_xiv_combat_sim/example_rotations/__init__.py
ama_xiv_combat_sim/example_rotations/add_caster_rotations_to_rotation_library.py
ama_xiv_combat_sim/example_rotations/add_healer_rotations_to_rotation_library.py
ama_xiv_combat_sim/example_rotations/add_melee_rotations_to_rotation_library.py
ama_xiv_combat_sim/example_rotations/add_ranged_rotations_to_rotation_library.py
ama_xiv_combat_sim/example_rotations/add_rotation_to_rotation_library.py
ama_xiv_combat_sim/example_rotations/add_tank_rotations_to_rotation_library.py
ama_xiv_combat_sim/example_rotations/example_rotation_utils.py
ama_xiv_combat_sim/example_rotations/get_example_rotations.py
ama_xiv_combat_sim/example_rotations/specific_rotations.py
ama_xiv_combat_sim/example_rotations/caster/blm.py
ama_xiv_combat_sim/example_rotations/caster/blm_data.py
ama_xiv_combat_sim/example_rotations/caster/pct.py
ama_xiv_combat_sim/example_rotations/caster/pct_data.py
ama_xiv_combat_sim/example_rotations/caster/rdm.py
ama_xiv_combat_sim/example_rotations/caster/rdm_data.py
ama_xiv_combat_sim/example_rotations/caster/smn.py
ama_xiv_combat_sim/example_rotations/caster/smn_data.py
ama_xiv_combat_sim/example_rotations/healer/ast.py
ama_xiv_combat_sim/example_rotations/healer/ast_data.py
ama_xiv_combat_sim/example_rotations/healer/sch.py
ama_xiv_combat_sim/example_rotations/healer/sch_data.py
ama_xiv_combat_sim/example_rotations/healer/sge.py
ama_xiv_combat_sim/example_rotations/healer/sge_data.py
ama_xiv_combat_sim/example_rotations/healer/whm.py
ama_xiv_combat_sim/example_rotations/healer/whm_data.py
ama_xiv_combat_sim/example_rotations/melee/drg.py
ama_xiv_combat_sim/example_rotations/melee/drg_data.py
ama_xiv_combat_sim/example_rotations/melee/mnk.py
ama_xiv_combat_sim/example_rotations/melee/mnk_data.py
ama_xiv_combat_sim/example_rotations/melee/nin.py
ama_xiv_combat_sim/example_rotations/melee/nin_data.py
ama_xiv_combat_sim/example_rotations/melee/rpr.py
ama_xiv_combat_sim-2026.1.14.1.dist-info/licenses/LICENSE
ama_xiv_combat_sim-2026.1.14.1.dist-info/METADATA
ama_xiv_combat_sim-2026.1.14.1.dist-info/WHEEL
ama_xiv_combat_sim-2026.1.14.1.dist-info/top_level.txt
ama_xiv_combat_sim-2026.1.14.1.dist-info/RECORD
