Metadata-Version: 2.4
Name: ama-xiv-combat-sim
Version: 2026.1.14.1
Summary: Ama's FF14 Combat Sim
Author-email: Amarantine Falena <simcode@xivraider.com>
Maintainer-email: Amarantine Falena <simcode@xivraider.com>
License:                                  Apache License
Project-URL: Homepage, https://github.com/Amarantine-xiv/Amas-FF14-Combat-Sim_source
Project-URL: Documentation, https://github.com/Amarantine-xiv/Amas-FF14-Combat-Sim_source
Project-URL: Repository, https://github.com/Amarantine-xiv/Amas-FF14-Combat-Sim_source.git
Project-URL: Bug Tracker, https://github.com/Amarantine-xiv/Amas-FF14-Combat-Sim_source/issues
Keywords: xiv,ff14,simulator
Classifier: Development Status :: 4 - Beta
Classifier: Programming Language :: Python
Requires-Python: >=3.8
License-File: LICENSE
Requires-Dist: numpy
Provides-Extra: gui
Requires-Dist: PyQt5; extra == "gui"
Provides-Extra: cli
Requires-Dist: rich; extra == "cli"
Requires-Dist: click; extra == "cli"
Dynamic: license-file
